{
    "P2_0_1_3": [
        "Risque {zone3} {periode1}, puis s’étendant également {zone2} {periode2}.",
        "Risque prévu {periode1_2} {zone3}, et s’étendant {periode2} {zone2}.",
        "Le risque touche {zone3} {periode1} puis s’étend également à {zone2} {periode2}.",
        "Le risque touche {zone3} {periode1_2} mais s’étend également à {zone2} {periode2}."
    ],
    "P3_2_4_7": [
        "Risque prévu {periode1_2_3} {zone3}, et s’étendant également {zone2} {periode1} et {zone1} {periode2}.",
        "Le risque est prévu {periode1_2_3} sur {zone3} et touche également {zone2} {periode1} et {zone1} {periode2}.",
        "Le risque est prévu {periode1_2_3} sur {zone3} et concerne également {zone2} {periode1} et {zone1} {periode2}."
    ],
    "P3_3_6_7": [
        "Risque prévu {periode1_2_3}. Il démarre seulement {periode2} {zone1} et cesse {periode3} {zone2}."
    ],
    "P3_2_5": [
        "{periode1_3} risque prévu {zone2}, mais {periode2} il se décale {zone1}."
    ],
    "P3_2_3_4": [
        "Prévu {zone3} {periode1}, le risque se décale ensuite sur le reste de la zone {periode2}, pour ne subsister que {zone2} {periode3}."
    ],
    "P3_4_5": [
        "Toute la zone est concernée par le risque {periode1}. Le risque reprend {periode3} {zone2}."
    ],
    "P3_1_3_5": [
        "Risque prévu {periode1} {zone3}, puis {zone2} {periode2}, avant de se généraliser {periode3}. "
    ],
    "P3_0_5_7": [
        "Risque prévu {periode1_2_3} {zone2_3}, même si on note un affaiblissement du risque {zone2} {periode2}."
    ],
    "P3_1_4": [
        "Risque prévu {zone2} {periode1}, puis {zone1} {periode3}."
    ],
    "P3_1_5_6": [
        "Le risque est prévu sur toute la zone à un moment ou l’autre {periode1_2_3}."
    ],
    "P3_4_6_7": [
        "Risque généralisé {periode1}, mais uniquement  {zone3} {periode3}.",
        "Toute la zone est concernée par le risque {periode1}, mais {periode3} il n’est plus prévu que {zone3}."
    ],
    "P3_2_3_7": [
        "Risque {zone3} {periode1}, qui se généralise {periode2}, puis persiste uniquement {zone2_3} {periode3}."
    ],
    "P3_5_7": [
        "Le risque est prévu {periode1_2_3}, même si on peut noter un affaiblissement du risque {periode2} {zone1}."
    ],
    "P3_2_6_7": [
        "Risque {zone2_3} {periode1}, qui se généralise {periode2}, puis persiste uniquement {zone3} {periode3}."
    ],
    "P2_0_1_2": [
        "Risque {zone3} {periode1}, se décalant {zone2} {periode2}."
    ],
    "P3_0_1_5": [
        "Risque prévu {periode1} {zone3}, puis reprenant {periode3} en s’étendant également {zone2}."
    ],
    "P3_5_6_7": [
        "Le risque est prévu sur toute la zone, à un moment ou l’autre, {periode1_2_3}.",
        "Le risque est prévu {periode1_2_3} sur toute la zone mais il épargne {zone1} {periode2} puis {zone3} [période3]."
    ],
    "P3_2_7": [
        "Risque {zone2} {periode1_2_3}, qui s’étend également {zone1} {periode2}."
    ],
    "P3_3_5_7": [
        "Risque prévu {periode1_2_3}. Il démarre seulement {periode2} {zone1}, alors qu’il s'atténue temporairement {zone2}."
    ],
    "P3_1_3_4": [
        "Prévu {periode1} {zone3}, le risque se décale {zone2} {periode2}, puis s’étend {zone3} {periode3}."
    ],
    "P3_0_2_7": [
        "Risque {zone3} {periode1_2_3}, qui s’étend également {zone2} {periode2}."
    ],
    "P3_1_2_6": [
        "Risque prévu {zone3} {periode1}, s’étendant {zone2} {periode3}, puis se décalant {zone1} {periode3}."
    ],
    "P3_1_5": [
        "Risque prévu {periode1} {zone2}, puis à nouveau {periode3} sur toute la zone."
    ],
    "P3_3_4_5": [
        "Le risque est prévu sur toute la zone, à un moment ou l’autre, {periode1_2_3}."
    ],
    "P3_2_5_6": [
        "Le risque est prévu sur toute la zone, à un moment ou l’autre, {periode1_2_3}."
    ],
    "P3_3_6": [
        "Risque prévu {zone2} {periode1}, se généralisant {periode2} et ne persistant que {zone1} {periode3}."
    ],
    "P3_2_3_5": [
        "Le risque est prévu sur toute la zone, à un moment ou l’autre, {periode1_2_3}."
    ],
    "P3_2_5_7": [
        "Le risque est prévu {periode1_2_3} {zone3}, mais également {zone2} {periode1_3} et {zone1} {periode2}."
    ],
    "P3_4_5_7": [
        "Prévu sur toute la zone {periode1}, le risque se limite {zone3} {periode2}, puis s’étend également {zone2} {periode3}."
    ],
    "P3_0_4_5": [
        "Risque {zone2_3} {periode1}, puis à nouveau {zone3} {periode3}."
    ],
    "P3_1_4_5": [
        "Risque prévu {periode1} {zone2_3}, puis à nouveau {periode3} {zone1_3}."
    ],
    "P3_1_2_5": [
        "Le risque est prévu sur toute la zone, à un moment ou l’autre, {periode1_2_3}."
    ],
    "P2_1_2_3": [
        "Risque attendu {zone2_3} {periode1}, ainsi que {zone1_3} {periode2}."
    ],
    "P3_1_4_6": [
        "Risque prévu {zone2_3} {periode1}, perdurant {periode2} {zone3}. {periode3}, le risque est attendu {zone1}."
    ],
    "P1_0_1": [
        "Risque prévu {zone2} {periode1}."
    ],
    "P3_2_3_6": [
        "Risque prévu sur toute la zone {periode2}, mais déjà {zone3} {periode1}, et perdurant {zone2} {periode3}."
    ],
    "P3_5_6": [
        "Risque sur toute la zone {periode1}, perdurant {zone2} {periode2}, et reprenant {zone1} {periode3}."
    ],
    "P3_3_5": [
        "{periode1}, risque prévu {zone2}, se décalant {periode2} {zone1}. {periode3}, toute la zone est concernée."
    ],
    "P3_4_5_6": [
        "Généralisé {periode1}, le risque se cantonne {zone3} {periode2}, puis {zone2} {periode3}."
    ],
    "P3_0_3_5": [
        "Risque prévu {zone3} {periode1_3}, et {zone2} {periode2_3}."
    ],
    "P3_0_5_6": [
        "{periode1} risque prévu {zone2_3}, perdurant {periode2} {zone3} et reprenant {periode3} {zone2}."
    ],
    "P3_1_5_7": [
        "Risque prévu {periode1} {zone2_3}, et {periode2} uniquement {zone3}, puis se généralisant {periode3}."
    ],
    "P3_0_2_5": [
        "Risque prévu {zone3} {periode1_3}, et {zone2} {periode2}."
    ],
    "P2_2_3": [
        "Toute la zone est touchée {periode1}, puis le risque se cantonne {zone2} {periode2}."
    ],
    "P2_1_3": [
        "Risque {zone2} {periode1}, se généralisant {periode2}."
    ],
    "P3_3_4_6": [
        "{periode1} risque prévu {zone2_3}. Puis, {periode2} {zone1_3}, et enfin {periode3} uniquement {zone1}."
    ],
    "P3_0_3_6": [
        "Risque prévu {periode1} {zone3}, s’étendant {periode2} {zone2}, où il perdure {periode3}."
    ],
    "P3_1_3_7": [
        "{zone3} {periode1}, le risque s’étend {periode2} {zone2}, puis toute la zone est touchée."
    ],
    "P3_1_2_7": [
        "Risque prévu {periode1_2_3} {zone3}, mais également {zone2} {periode2}, et {zone1} {periode3}."
    ],
    "P3_0_5": [
        "Risque prévu {periode1_3} {zone2}."
    ],
    "P2_0_2_3": [
        " Risque {zone2_3} {periode1}, perdurant uniquement {zone3} {periode2}."
    ],
    "P3_1_4_7": [
        "Risque prévu {periode1_2_3} {zone3}, s’étendant {zone2} {periode1}, et {zone1} {periode3}."
    ],
    "P3_3_5_6": [
        "Le risque est prévu sur toute la zone, à un moment ou l’autre, {periode1_2_3}."
    ],
    "P3_2_4_5": [
        "Risque prévu {periode1} {zone2_3}, se décalant {periode2} {zone1}, puis reprenant {periode3} {zone3}."
    ],
    "P2_1_2": [
        "Risque {zone2} {periode1}, se décalant {zone1} {periode2}."
    ],
    "P3_1_3_6": [
        "{zone3} {periode1}, le risque s’étend {zone2} {periode2}, puis se décale {zone1_2} {periode3}."
    ],
    "P3_1_2_4": [
        "Risque prévu {zone3} {periode1}, se décalant {zone2} {periode2}, puis {zone1} {periode3}."
    ],
    "P3_0_1_4": [
        "Risque prévu {periode1} {zone3}, puis {zone2} {periode3}."
    ]
}